myclustering/__init__.py
myclustering/dbscan/__init__.py
myclustering/dbscan/dbscan.py
myclustering/dbscan/visualization.py
myclustering/kmeans/__init__.py
myclustering/kmeans/elbow.py
myclustering/kmeans/kmeans.py
myclustering/kmeans/silhouette.py
myclustering/kmeans/visualization.py
myclustering/pca/__init__.py
myclustering/pca/pca.py
myclustering-0.1.0.dist-info/AUTHORS.rst
myclustering-0.1.0.dist-info/LICENSE
myclustering-0.1.0.dist-info/METADATA
myclustering-0.1.0.dist-info/WHEEL
myclustering-0.1.0.dist-info/top_level.txt
myclustering-0.1.0.dist-info/RECORD
