Metadata-Version: 2.1
Name: myclustering
Version: 0.1.0
Summary: Python package for clustering
Home-page: https://github.com/Natali-Hovhannisyan/DS233_Python_Package
Author: Natali Hovhannisyan
Author-email: natalihovhannisyan00@gmail.com
License: MIT license
Keywords: myclustering
Platform: UNKNOWN
Classifier: Development Status :: 2 - Pre-Alpha
Classifier: Intended Audience :: Developers
Classifier: License :: OSI Approved :: MIT License
Classifier: Natural Language :: English
Classifier: Programming Language :: Python :: 3
Classifier: Programming Language :: Python :: 3.6
Classifier: Programming Language :: Python :: 3.7
Classifier: Programming Language :: Python :: 3.8
Requires-Python: >=3.6
Requires-Dist: numpy
Requires-Dist: matplotlib
